CHANGES.md
CHECKSUM
CONTRIBUTING.md
LICENSE
MANIFEST.in
README.md
VERSION
gsutil
gsutil.py
setup.py
gslib/README
gslib/__init__.py
gslib/__main__.py
gslib/boto_resumable_upload.py
gslib/boto_translation.py
gslib/bucket_listing_ref.py
gslib/cloud_api.py
gslib/cloud_api_delegator.py
gslib/command.py
gslib/command_argument.py
gslib/command_runner.py
gslib/context_config.py
gslib/cred_types.py
gslib/cs_api_map.py
gslib/daisy_chain_wrapper.py
gslib/devshell_auth_plugin.py
gslib/discard_messages_queue.py
gslib/exception.py
gslib/file_part.py
gslib/gcs_json_api.py
gslib/gcs_json_credentials.py
gslib/gcs_json_media.py
gslib/help_provider.py
gslib/iamcredentials_api.py
gslib/impersonation_credentials.py
gslib/kms_api.py
gslib/lazy_wrapper.py
gslib/metrics.py
gslib/metrics_reporter.py
gslib/metrics_tuple.py
gslib/name_expansion.py
gslib/no_op_auth_plugin.py
gslib/no_op_credentials.py
gslib/parallel_tracker_file.py
gslib/plurality_checkable_iterator.py
gslib/progress_callback.py
gslib/project_id.py
gslib/pubsub_api.py
gslib/resumable_streaming_upload.py
gslib/seek_ahead_thread.py
gslib/sig_handling.py
gslib/storage_uri_builder.py
gslib/storage_url.py
gslib/tab_complete.py
gslib/thread_message.py
gslib/tracker_file.py
gslib/tz_utc.py
gslib/ui_controller.py
gslib/wildcard_iterator.py
gslib/addlhelp/__init__.py
gslib/addlhelp/acls.py
gslib/addlhelp/command_opts.py
gslib/addlhelp/crc32c.py
gslib/addlhelp/creds.py
gslib/addlhelp/dev.py
gslib/addlhelp/encoding.py
gslib/addlhelp/metadata.py
gslib/addlhelp/naming.py
gslib/addlhelp/prod.py
gslib/addlhelp/security.py
gslib/addlhelp/shim.py
gslib/addlhelp/support.py
gslib/addlhelp/versions.py
gslib/commands/__init__.py
gslib/commands/acl.py
gslib/commands/autoclass.py
gslib/commands/bucketpolicyonly.py
gslib/commands/cat.py
gslib/commands/compose.py
gslib/commands/config.py
gslib/commands/cors.py
gslib/commands/cp.py
gslib/commands/defacl.py
gslib/commands/defstorageclass.py
gslib/commands/du.py
gslib/commands/hash.py
gsutil.egg-info/PKG-INFO
gsutil.egg-info/SOURCES.txt
gsutil.egg-info/dependency_links.txt
gsutil.egg-info/entry_points.txt
gsutil.egg-info/requires.txt
gsutil.egg-info/top_level.txt
gsutil.egg-info/zip-safe