Metadata-Version: 2.4
Name: gsutil
Version: 5.35
Summary: A command line tool for interacting with cloud storage services.
Home-page: https://cloud.google.com/storage/docs/gsutil
Download-URL: https://cloud.google.com/storage/docs/gsutil_install
Author: Google Inc.
Author-email: buganizer-system+187143@google.com
License: Apache 2.0
Platform: any
Classifier: Development Status :: 5 - Production/Stable
Classifier: Environment :: Console
Classifier: Intended Audience :: Developers
Classifier: Intended Audience :: System Administrators
Classifier: License :: OSI Approved :: Apache Software License
Classifier: Natural Language :: English
Classifier: Programming Language :: Python
Classifier: Programming Language :: Python :: 3
Classifier: Programming Language :: Python :: 3.9
Classifier: Programming Language :: Python :: 3.10
Classifier: Programming Language :: Python :: 3.11
Classifier: Programming Language :: Python :: 3.12
Classifier: Programming Language :: Python :: 3.13
Classifier: Topic :: System :: Filesystems
Classifier: Topic :: Utilities
Requires-Python: >=3.9, <3.14
License-File: LICENSE
Requires-Dist: argcomplete>=3.6.2
Requires-Dist: crcmod>=1.7
Requires-Dist: fasteners>=0.14.1
Requires-Dist: gcs-oauth2-boto-plugin>=3.3
Requires-Dist: google-apitools>=0.5.32
Requires-Dist: httplib2==0.20.4
Requires-Dist: google-reauth>=0.1.0
Requires-Dist: mock<=3.0.5,>=2.0.0; python_version < "3.3"
Requires-Dist: monotonic>=1.4
Requires-Dist: pyOpenSSL<=24.2.1,>=0.13
Requires-Dist: retry_decorator>=1.0.0
Requires-Dist: six>=1.17.0
Requires-Dist: google-auth[aiohttp]==2.39.0
Requires-Dist: google-auth-httplib2>=0.2.0
Dynamic: author
Dynamic: author-email
Dynamic: classifier
Dynamic: description
Dynamic: description-content-type
Dynamic: download-url
Dynamic: home-page
Dynamic: license
Dynamic: license-file
Dynamic: platform
Dynamic: requires-dist
Dynamic: requires-python
Dynamic: summary
